Metadata-Version: 2.1
Name: j5gnpuiwerbngpiutbgn0iutb0p
Version: 0.0.1
Summary: Dependency confusion Attack
Author: techghoshal
Author-email: techghoshal@gmail.com
Requires-Dist: requests
